cr_analysis/__init__.py
cr_analysis/main.py
cr_analysis-4.2.9.2.dist-info/METADATA
cr_analysis-4.2.9.2.dist-info/WHEEL
cr_analysis-4.2.9.2.dist-info/top_level.txt
cr_analysis-4.2.9.2.dist-info/RECORD
