Metadata-Version: 2.1
Name: cr-analysis
Version: 4.2.9.2
Summary: Visualization tool by Python for circadian analysis.
Home-page: https://github.com/TOOOOOOMY/cr-analysis
Author: TOOOOOOMY
Author-email: 10talatgi@gmail.com
License: MIT
